stupidf-0.5.1.dist-info/METADATA
stupidf-0.5.1.dist-info/WHEEL
stupidf-0.5.1.dist-info/licenses/LICENSE
stupidf/__init__.py
stupidf/stupidf.abi3.so
stupidf-0.5.1.dist-info/RECORD
