Metadata-Version: 2.4
Name: stupidf
Version: 0.5.1
Requires-Dist: polars
License-File: LICENSE
Summary: Parsing of STDF file format to DataFrame with Python bindings
Keywords: semiconductor,stdf,ate
License: MIT
Project-URL: Source Code, https://github.com/jlazear/stupidf
